setup.cfg
setup.py
./bin/leela
./bin/leela-worker
leela/__init__.py
leela.egg-info/PKG-INFO
leela.egg-info/SOURCES.txt
leela.egg-info/dependency_links.txt
leela.egg-info/requires.txt
leela.egg-info/top_level.txt
leela/core/__init__.py
leela/core/application.py
leela/core/decorators.py
leela/core/middleware.py
leela/core/orm.py
leela/core/service.py
leela/core/sessions.py
leela/utils/__init__.py
leela/utils/config.py
leela/utils/daemon3x.py
leela/utils/dispatcher_daemon.py
leela/utils/logger.py
leela/utils/test_utils.py