Metadata-Version: 1.1
Name: leela
Version: 0.9.1
Summary: Leela web framework.
Home-page: https://github.com/fabregas/leela
Author: Kostiantyn Andrusenko
Author-email: kksstt@gmail.com
License: http://www.apache.org/licenses/LICENSE-2.0
Download-URL: https://github.com/fabregas/leela/tarball/0.9.1
Keywords: web,asyncio
Platform: UNKNOWN
